automatheque/__init__.py
automatheque/configuration.py
automatheque/constantes.py
automatheque/exceptions.py
automatheque/log.py
automatheque/py.typed
automatheque/conception/__init__.py
automatheque/conception/structures/__init__.py
automatheque/conception/structures/adaptateur.py
automatheque/conception/structures/borg.py
automatheque/conception/structures/fabrique.py
automatheque/conception/structures/monteur.py
automatheque/conception/structures/registre.py
automatheque/conception/structures/singleton.py
automatheque/greffon/__init__.py
automatheque/greffon/capacite.py
automatheque/greffon/greffon.py
automatheque/greffon/registre.py
automatheque/plugin/plugin.py
automatheque/suivi/__init__.py
automatheque/suivi/journal.py
automatheque/suivi/ports.py
automatheque/suivi/suivi.py
automatheque/suivi/adaptateurs/__init__.py
automatheque/suivi/adaptateurs/repertoire.py
automatheque/util/__init__.py
automatheque/util/classe.py
automatheque/util/dependances_externes.py
automatheque/util/fichier.py
automatheque/util/repertoire.py
automatheque/util/script.py
automatheque/util/structures_python.py
automatheque-0.9.9.dist-info/METADATA
automatheque-0.9.9.dist-info/WHEEL
automatheque-0.9.9.dist-info/top_level.txt
automatheque-0.9.9.dist-info/RECORD
