Metadata-Version: 2.1
Name: automatheque
Version: 0.9.9
Summary: Bibliothèque pour se faciliter le scripting !
Author-email: Marc <githubmarc@maj44.com>
License: GPLv3.0
Project-URL: Home, https://github.com/jaegerbobomb/automatheque/tree/main/src/automatheque/
Project-URL: Repository, https://github.com/jaegerbobomb/automatheque.git
Requires-Python: >=3.8
Requires-Dist: docopt
Requires-Dist: pytz
Requires-Dist: configparser
Requires-Dist: pyyaml
Requires-Dist: attrs>=19.2
Provides-Extra: dev
Requires-Dist: pytest; extra == "dev"
